edge_logger/__init__.py
edge_logger/edge_logger.py
edge_logger-0.0.11.dist-info/LICENSE
edge_logger-0.0.11.dist-info/METADATA
edge_logger-0.0.11.dist-info/WHEEL
edge_logger-0.0.11.dist-info/RECORD
