Metadata-Version: 2.1
Name: edge-logger
Version: 0.0.11
Summary: Logging Package for Edge Computing
License: MIT
Author: reinaldopenno
Author-email: rapenno@gmail.com
Requires-Python: >=3.10,<4.0
Classifier: License :: OSI Approved :: MIT License
Classifier: Programming Language :: Python :: 3
Classifier: Programming Language :: Python :: 3.10
Classifier: Programming Language :: Python :: 3.11
Requires-Dist: requests (>=2.29.0,<3.0.0)
